{"filename": "Trade_Report_Combined_11-05-2026.xlsx", "recordsProcessed": "319", "recordsFiltered": "51", "duplicatesRemoved": "28", "fileStats": [{"filename": "Copy of Renderways_Technologies Technologies Private Limited 27th apr.xlsx", "total": 197, "filtered": 48}, {"filename": "Flex_WIP_ASP_Report (1).xlsx", "total": 122, "filtered": 31}], "cityStats": {"Chennai": 31, "Salem": 12, "Vellore": 8}, "gridData": [{"Ticket No": "WO-034232927", "Case Id": 5158707873, "Current Remarks": "", "WIP Aging": 2, "WIP Aging Category": "  24 to 48Hr (NBD)", "Status": "Visit Estimate", "HP Owner": "Actionable", "Product Name": "HP ProBook 440 G8 Notebook PC (61G04AV)", "Product Serial No": "5CD305520D", "Product Type": "PC", "ASP City": "Salem"}, {"Ticket No": "WO-034203943", "Case Id": 5158101562, "Current Remarks": "", "WIP Aging": 4, "WIP Aging Category": " 3 to 5 Days", "Status": "Partner Parts Hold", "HP Owner": "SSC Pending", "Product Name": "HP 240 G8 Notebook PC (43Q71AV)", "Product Serial No": "5CG14508X3", "Product Type": "PC", "ASP City": "Chennai"}, {"Ticket No": "WO-034245458", "Case Id": 5158755678, "Current Remarks": "", "WIP Aging": 1, "WIP Aging Category": "   4 to 24Hr (SBD)", "Status": "Visit Estimate", "HP Owner": "Actionable", "Product Name": "HP Smart Tank 585 All-in-One Printer", "Product Serial No": "TH42S6T1FK", "Product Type": "Print", "ASP City": "Chennai"}, {"Ticket No": "WO-034234092", "Case Id": 5158703485, "Current Remarks": "", "WIP Aging": 2, "WIP Aging Category": "  24 to 48Hr (NBD)", "Status": "Visit Quote To Customer", "HP Owner": "Actionable", "Product Name": "HP Smart Tank 790 All-in-One", "Product Serial No": "CN3C7170ZM", "Product Type": "Print", "ASP City": "Chennai"}, {"Ticket No": "WO-033951503", "Case Id": 5157581371, "Current Remarks": "The customer is not answering my calls.", "WIP Aging": 4, "WIP Aging Category": " 3 to 5 Days", "Status": "Partner Cust Delay - Customer Not Responded", "HP Owner": "Actionable -Customer Pending", "Product Name": "HP 240 G8 Notebook PC (43Q77AV)", "Product Serial No": "5CG22528MZ", "Product Type": "PC", "ASP City": "Salem"}, {"Ticket No": "WO-034216516", "Case Id": 5158616312, "Current Remarks": "", "WIP Aging": 3, "WIP Aging Category": "  48 to 72Hr (2BD)", "Status": "Visit Quote To Customer", "HP Owner": "Actionable", "Product Name": "HP Smart Tank 580 All-in-One Printer", "Product Serial No": "TH49B8T0DY", "Product Type": "Print", "ASP City": "Chennai"}, {"Ticket No": "WO-034194821", "Case Id": 5158559321, "Current Remarks": "", "WIP Aging": 5, "WIP Aging Category": " 3 to 5 Days", "Status": "Visitation Accepted", "HP Owner": "Actionable", "Product Name": "HP LaserJet Pro M1136 Multifunction Printer", "Product Serial No": "CNJ8FC9D8S", "Product Type": "Print", "ASP City": "Chennai"}, {"Ticket No": "WO-034195347", "Case Id": 5158560196, "Current Remarks": "", "WIP Aging": 5, "WIP Aging Category": " 3 to 5 Days", "Status": "Visit Quote To Customer", "HP Owner": "Actionable", "Product Name": "HP Pavilion x360 14 inch 2-in-1 Laptop PC 14-ek0000 (54B25AV)", "Product Serial No": "8CG3140NCC", "Product Type": "PC", "ASP City": "Chennai"}, {"Ticket No": "WO-034179746", "Case Id": 5158496369, "Current Remarks": "", "WIP Aging": 6, "WIP Aging Category": " 6 to 10 Days", "Status": "Visit Estimate", "HP Owner": "Actionable", "Product Name": "HP Smart Tank 675 All-in-One", "Product Serial No": "CN42Q690VR", "Product Type": "Print", "ASP City": "Vellore"}, {"Ticket No": "WO-034193359", "Case Id": 5157939992, "Current Remarks": "", "WIP Aging": 5, "WIP Aging Category": " 3 to 5 Days", "Status": "Visit Quote To Customer", "HP Owner": "Actionable", "Product Name": "HP OmniBook X Flip 14 inch 2-in-1 Laptop Next Gen AI PC 14-fm0000 (AK4", "Product Serial No": "8CG5112W7R", "Product Type": "PC", "ASP City": "Vellore"}, {"Ticket No": "WO-034193009", "Case Id": 5158541977, "Current Remarks": "", "WIP Aging": 5, "WIP Aging Category": " 3 to 5 Days", "Status": "Visit Quote To Customer", "HP Owner": "Actionable", "Product Name": "HP Ink Tank Wireless 419", "Product Serial No": "CN21H8D1C4", "Product Type": "Print", "ASP City": "Chennai"}, {"Ticket No": "WO-034194720", "Case Id": 5158558747, "Current Remarks": "", "WIP Aging": 5, "WIP Aging Category": " 3 to 5 Days", "Status": "Visit Quote To Customer", "HP Owner": "Actionable", "Product Name": "HP Smart Tank 530 Wireless All-in-One", "Product Serial No": "CN49N7S0KF", "Product Type": "Print", "ASP City": "Chennai"}, {"Ticket No": "WO-034210756", "Case Id": 5158480530, "Current Remarks": "", "WIP Aging": 4, "WIP Aging Category": " 3 to 5 Days", "Status": "Visit Quote To Customer", "HP Owner": "Actionable", "Product Name": "HP Smart Tank 585 All-in-One Printer", "Product Serial No": "TH46O8W10T", "Product Type": "Print", "ASP City": "Chennai"}, {"Ticket No": "WO-034179623", "Case Id": 5158497813, "Current Remarks": "", "WIP Aging": 6, "WIP Aging Category": " 6 to 10 Days", "Status": "Visit Quote To Customer", "HP Owner": "Actionable", "Product Name": "HP LaserJet Tank MFP 2606sdw Printer", "Product Serial No": "VNF4829983", "Product Type": "Print", "ASP City": "Salem"}, {"Ticket No": "WO-034193181", "Case Id": 5158554509, "Current Remarks": "", "WIP Aging": 5, "WIP Aging Category": " 3 to 5 Days", "Status": "Visit Quote To Customer", "HP Owner": "Actionable", "Product Name": "HP Neverstop Laser MFP 1200w", "Product Serial No": "CNBRP9HBYX", "Product Type": "Print", "ASP City": "Chennai"}, {"Ticket No": "WO-034205856", "Case Id": 5158596035, "Current Remarks": "", "WIP Aging": 4, "WIP Aging Category": " 3 to 5 Days", "Status": "Visit Quote To Customer", "HP Owner": "Actionable", "Product Name": "HP Smart Tank 581 All-in-One Printer", "Product Serial No": "CN36C5C44W", "Product Type": "Print", "ASP City": "Chennai"}, {"Ticket No": "WO-034200817", "Case Id": 5158543398, "Current Remarks": "", "WIP Aging": 4, "WIP Aging Category": " 3 to 5 Days", "Status": "Visitation Accepted", "HP Owner": "Actionable", "Product Name": "HP Smart Tank 675 All-in-One", "Product Serial No": "CN2815700Z", "Product Type": "Print", "ASP City": "Chennai"}, {"Ticket No": "WO-034246687", "Case Id": 5158763971, "Current Remarks": "", "WIP Aging": 1, "WIP Aging Category": "   4 to 24Hr (SBD)", "Status": "Partner Accept", "HP Owner": "Actionable", "Product Name": "HP Laser 108w", "Product Serial No": "CNB3Q1D41L", "Product Type": "Print", "ASP City": "Chennai"}, {"Ticket No": "WO-034096358", "Case Id": 5158171509, "Current Remarks": "", "WIP Aging": 12, "WIP Aging Category": "11 to 15 Days", "Status": "Engg Assigned", "HP Owner": "Scheduled", "Product Name": "HP Ink Tank Wireless 415", "Product Serial No": "CN19R8D395", "Product Type": "Print", "ASP City": "Chennai"}, {"Ticket No": "WO-033961127", "Case Id": 5157607425, "Current Remarks": "", "WIP Aging": 24, "WIP Aging Category": "15 to 30 Days", "Status": "Additional Part", "HP Owner": "Partner backend", "Product Name": "HP Laser MFP 1188w Printer", "Product Serial No": "CNB1RDT3KT", "Product Type": "Print", "ASP City": "Vellore"}, {"Ticket No": "WO-034114735", "Case Id": 5158245376, "Current Remarks": "", "WIP Aging": 11, "WIP Aging Category": "11 to 15 Days", "Status": "Engg Assigned", "HP Owner": "Scheduled", "Product Name": "HP Smart Tank 580 All-in-One Printer", "Product Serial No": "CN31K2C15F", "Product Type": "Print", "ASP City": "Chennai"}, {"Ticket No": "WO-034164989", "Case Id": 5158444830, "Current Remarks": "", "WIP Aging": 7, "WIP Aging Category": " 6 to 10 Days", "Status": "Partner Parts Hold", "HP Owner": "SSC Pending", "Product Name": "HP DeskJet Ink Advantage 2778 All-in-One Printer", "Product Serial No": "CN36KDZKVV", "Product Type": "Print", "ASP City": "Chennai"}, {"Ticket No": "WO-033995470", "Case Id": 5157731241, "Current Remarks": "", "WIP Aging": 21, "WIP Aging Category": "15 to 30 Days", "Status": "Additional Part", "HP Owner": "Partner backend", "Product Name": "HP Smart Tank 580 All-in-One Printer", "Product Serial No": "TH43N6W1DG", "Product Type": "Print", "ASP City": "Chennai"}, {"Ticket No": "WO-034145457", "Case Id": 5158356983, "Current Remarks": "", "WIP Aging": 9, "WIP Aging Category": " 6 to 10 Days", "Status": "Visit Estimate", "HP Owner": "Actionable", "Product Name": "HP Smart Tank 790 All-in-One", "Product Serial No": "CN3C717125", "Product Type": "Print", "ASP City": "Vellore"}, {"Ticket No": "WO-034078028", "Case Id": 5158050687, "Current Remarks": "", "WIP Aging": 14, "WIP Aging Category": "11 to 15 Days", "Status": "Engg Assigned", "HP Owner": "Scheduled", "Product Name": "HP Ink Tank Wireless 416", "Product Serial No": "CN22H8D1Y5", "Product Type": "Print", "ASP City": "Chennai"}, {"Ticket No": "WO-034130807", "Case Id": 5158231027, "Current Remarks": "", "WIP Aging": 10, "WIP Aging Category": " 6 to 10 Days", "Status": "Engg Assigned", "HP Owner": "Scheduled", "Product Name": "HP Smart Tank 675 All-in-One", "Product Serial No": "CN37I590WX", "Product Type": "Print", "ASP City": "Vellore"}, {"Ticket No": "WO-034164401", "Case Id": 5158397686, "Current Remarks": "", "WIP Aging": 7, "WIP Aging Category": " 6 to 10 Days", "Status": "Additional Part", "HP Owner": "Partner backend", "Product Name": "HP Ink Tank Wireless 416", "Product Serial No": "CN14T8D3H8", "Product Type": "Print", "ASP City": "Chennai"}, {"Ticket No": "WO-034164339", "Case Id": 5158445473, "Current Remarks": "", "WIP Aging": 7, "WIP Aging Category": " 6 to 10 Days", "Status": "Visit Quote To Customer", "HP Owner": "Actionable", "Product Name": "HP Smart Tank 585 All-in-One Printer", "Product Serial No": "CN3CB25HQ5", "Product Type": "Print", "ASP City": "Chennai"}, {"Ticket No": "WO-034137215", "Case Id": 5157659997, "Current Remarks": "", "WIP Aging": 9, "WIP Aging Category": " 6 to 10 Days", "Status": "Partner Parts Hold", "HP Owner": "SSC Pending", "Product Name": "OMEN by HP 16.1 inch Gaming Laptop PC 16-xf0000 (758R1AV)", "Product Serial No": "CND3291NX1", "Product Type": "PC", "ASP City": "Salem"}, {"Ticket No": "WO-034159475", "Case Id": 5158416894, "Current Remarks": "", "WIP Aging": 8, "WIP Aging Category": " 6 to 10 Days", "Status": "Visit Estimate", "HP Owner": "Actionable", "Product Name": "HP Smart Tank 589 All-in-One Printer", "Product Serial No": "TH48O8W20Z", "Product Type": "Print", "ASP City": "Vellore"}, {"Ticket No": "WO-033986045", "Case Id": 5157714485, "Current Remarks": "", "WIP Aging": 5, "WIP Aging Category": " 3 to 5 Days", "Status": "Partner Cust Delay - Customer Rescheduled", "HP Owner": "Actionable -Customer Pending", "Product Name": "HP ProBook 440 G8 Notebook PC (488B7AV)", "Product Serial No": "1N114702R9", "Product Type": "PC", "ASP City": "Vellore"}, {"Ticket No": "WO-034021686", "Case Id": 5157668680, "Current Remarks": "Good part received", "WIP Aging": 11, "WIP Aging Category": "11 to 15 Days", "Status": "Good Part Received", "HP Owner": "Actionable", "Product Name": "HP EliteBook 640 14 inch G9 Notebook PC (67W58AV)", "Product Serial No": "5CD3428K8R", "Product Type": "PC", "ASP City": "Chennai"}, {"Ticket No": "WO-034103254", "Case Id": 5158037843, "Current Remarks": "", "WIP Aging": 12, "WIP Aging Category": "11 to 15 Days", "Status": "Visit Quote To Customer", "HP Owner": "Actionable", "Product Name": "HP Laser MFP 1188w Printer", "Product Serial No": "CNB1R539HJ", "Product Type": "Print", "ASP City": "Salem"}, {"Ticket No": "WO-034161338", "Case Id": 5157579203, "Current Remarks": "", "WIP Aging": 6, "WIP Aging Category": " 6 to 10 Days", "Status": "Partner Cust Delay - Customer Rescheduled", "HP Owner": "Actionable -Customer Pending", "Product Name": "HP ProBook 440 G8 Notebook PC (488B7AV)", "Product Serial No": "1N114703DD", "Product Type": "PC", "ASP City": "Salem"}, {"Ticket No": "WO-034144871", "Case Id": 5158362225, "Current Remarks": "printer slow issue", "WIP Aging": 9, "WIP Aging Category": " 6 to 10 Days", "Status": "Partner Onsite", "HP Owner": "Scheduled", "Product Name": "HP Smart Tank 580 All-in-One Printer", "Product Serial No": "TH49A8W284", "Product Type": "Print", "ASP City": "Salem"}, {"Ticket No": "WO-033940434", "Case Id": 5157390536, "Current Remarks": "", "WIP Aging": 26, "WIP Aging Category": "15 to 30 Days", "Status": "Additional Part", "HP Owner": "Partner backend", "Product Name": "HP Smart Tank 790 All-in-One", "Product Serial No": "TH4735D0PT", "Product Type": "Print", "ASP City": "Chennai"}, {"Ticket No": "WO-034164810", "Case Id": 5158411953, "Current Remarks": "", "WIP Aging": 7, "WIP Aging Category": " 6 to 10 Days", "Status": "Visitation Accepted", "HP Owner": "Actionable", "Product Name": "HP Smart Tank 790 All-in-One", "Product Serial No": "CN267470Y5", "Product Type": "Print", "ASP City": "Chennai"}, {"Ticket No": "WO-034236907", "Case Id": 5158719249, "Current Remarks": "", "WIP Aging": 2, "WIP Aging Category": "  24 to 48Hr (NBD)", "Status": "Visit Estimate", "HP Owner": "Actionable", "Product Name": "HP Smart Tank 675 All-in-One", "Product Serial No": "TH4926B13X", "Product Type": "Print", "ASP City": "Chennai"}, {"Ticket No": "WO-034187821", "Case Id": 5158535204, "Current Remarks": "", "WIP Aging": 5, "WIP Aging Category": " 3 to 5 Days", "Status": "Visitation Accepted", "HP Owner": "Actionable", "Product Name": "HP Smart Tank 675 All-in-One", "Product Serial No": "TH4C36D14S", "Product Type": "Print", "ASP City": "Chennai"}, {"Ticket No": "WO-034023771", "Case Id": 5157814117, "Current Remarks": "", "WIP Aging": 18, "WIP Aging Category": "15 to 30 Days", "Status": "Engineer Assignment Pending", "HP Owner": "Actionable", "Product Name": "HP Smart Tank 670 All-in-One", "Product Serial No": "TH49I6D16W", "Product Type": "Print", "ASP City": "Vellore"}, {"Ticket No": "WO-034010831", "Case Id": 5157812370, "Current Remarks": "", "WIP Aging": 15, "WIP Aging Category": "11 to 15 Days", "Status": "Customer Denied Service", "HP Owner": "Actionable -Customer Pending", "Product Name": "HP 280 Pro G6 Microtower PC (8QY87AV)", "Product Serial No": "1N122409DK", "Product Type": "PC", "ASP City": "Salem"}, {"Ticket No": "WO-034203210", "Case Id": 5158597379, "Current Remarks": "", "WIP Aging": 4, "WIP Aging Category": " 3 to 5 Days", "Status": "Visitation Accepted", "HP Owner": "Actionable", "Product Name": "HP Laser MFP 1188w Printer", "Product Serial No": "CNB1R3SC0W", "Product Type": "Print", "ASP City": "Chennai"}, {"Ticket No": "WO-034237734", "Case Id": 5158706389, "Current Remarks": "", "WIP Aging": 2, "WIP Aging Category": "  24 to 48Hr (NBD)", "Status": "Visit Estimate", "HP Owner": "Actionable", "Product Name": "HP Smart Tank 670 All-in-One", "Product Serial No": "CN2C75904D", "Product Type": "Print", "ASP City": "Chennai"}, {"Ticket No": "WO-034055550", "Case Id": 5157996816, "Current Remarks": "", "WIP Aging": 16, "WIP Aging Category": "15 to 30 Days", "Status": "Visit Quote To Customer", "HP Owner": "Actionable", "Product Name": "HP Smart Tank 580 All-in-One Printer", "Product Serial No": "CN2AR1BH04", "Product Type": "Print", "ASP City": "Salem"}, {"Ticket No": "WO-034025354", "Case Id": 5157874166, "Current Remarks": "", "WIP Aging": 18, "WIP Aging Category": "15 to 30 Days", "Status": "Visit Quote To Customer", "HP Owner": "Actionable", "Product Name": "HP Smart Tank 516 Wireless All-in-One", "Product Serial No": "CN24T4S0K2", "Product Type": "Print", "ASP City": "Salem"}, {"Ticket No": "WO-034075625", "Case Id": 5157986642, "Current Remarks": "", "WIP Aging": 14, "WIP Aging Category": "11 to 15 Days", "Status": "Visit Quote To Customer", "HP Owner": "Actionable", "Product Name": "HP LaserJet Tank 1020w Printer", "Product Serial No": "VNC3J26057", "Product Type": "Print", "ASP City": "Salem"}, {"Ticket No": "WO-034007215", "Case Id": 5157769458, "Current Remarks": "", "WIP Aging": 20, "WIP Aging Category": "15 to 30 Days", "Status": "Visit Quote To Customer", "HP Owner": "Actionable", "Product Name": "HP Smart Tank 670 All-in-One", "Product Serial No": "TH46Q6D0WT", "Product Type": "Print", "ASP City": "Salem"}, {"Ticket No": "WO-034139130", "Case Id": 5158346440, "Current Remarks": "Payment Pending", "WIP Aging": 9, "WIP Aging Category": " 6 to 10 Days", "Status": "Partner Cust Delay - Customer Not Responded", "HP Owner": "Actionable -Customer Pending", "Product Name": "HP Ink Tank 319", "Product Serial No": "CN21H6D2FV", "Product Type": "Print", "ASP City": "Chennai"}, {"Ticket No": "WO-034249710", "Case Id": 5158775074, "Current Remarks": "", "WIP Aging": "", "WIP Aging Category": "", "Status": "Visit Quote To Customer", "HP Owner": "", "Product Name": "HP Smart Tank 580 All-in-One Printer", "Product Serial No": "CN3243C1B0", "Product Type": "", "ASP City": "Chennai"}, {"Ticket No": "WO-034254514", "Case Id": 5158789135, "Current Remarks": "", "WIP Aging": "", "WIP Aging Category": "", "Status": "FCT To Call Customer", "HP Owner": "", "Product Name": "HP Color LaserJet Pro MFP M183fw", "Product Serial No": "VNC3Y04517", "Product Type": "", "ASP City": "Chennai"}, {"Ticket No": "WO-034256453", "Case Id": 5158763326, "Current Remarks": "", "WIP Aging": "", "WIP Aging Category": "", "Status": "FCT To Call Customer", "HP Owner": "", "Product Name": "HP Smart Tank 530 Wireless All-in-One", "Product Serial No": "CN18D4S09H", "Product Type": "", "ASP City": "Chennai"}]}